cucim-23.10.0.dist-info/WHEEL
cucim-23.10.0.dist-info/AUTHORS.md
cucim-23.10.0.dist-info/RECORD
cucim-23.10.0.dist-info/METADATA
cucim-23.10.0.dist-info/PKG-INFO (lee8rx-MS-7B05's conflicted copy 2022-01-09)
cucim-23.10.0.dist-info/top_level.txt
cucim-23.10.0.dist-info/entry_points.txt
cucim/__main__.py
cucim/__init__.pyi
cucim/_misc.py
cucim/cufile.log
cucim/medial_axis_lookup_table.npz
cucim/_version.py
cucim/time.py
cucim/__init__.py
cucim/skimage/__init__.pyi
cucim/skimage/test1.cpp
cucim/skimage/cufile.log
cucim/skimage/temp.py
cucim/skimage/_temp.py
cucim/skimage/__init__.py
cucim/skimage/feature/_hessian_det_appx.py
cucim/skimage/feature/util.py
cucim/skimage/feature/brief_pythran.py
cucim/skimage/feature/blob.py
cucim/skimage/feature/peak.py
cucim/skimage/feature/cufile.log
cucim/skimage/feature/corner.py
cucim/skimage/feature/template.py
cucim/skimage/feature/_daisy.py
cucim/skimage/feature/_canny.py
cucim/skimage/feature/match.py
cucim/skimage/feature/_basic_features.py
cucim/skimage/feature/__init__.py
cucim/skimage/feature/tests/test_match.py
cucim/skimage/feature/tests/test_daisy.py
cucim/skimage/feature/tests/test_basic_features.py
cucim/skimage/feature/tests/test_canny.py
cucim/skimage/feature/tests/cufile.log
cucim/skimage/feature/tests/test_peak.py
cucim/skimage/feature/tests/test_template.py
cucim/skimage/feature/tests/test_blob.py
cucim/skimage/feature/tests/test_corner.py
cucim/skimage/feature/cuda/blob.cu
cucim/skimage/feature/cuda/_hessian_det_appx.cu
cucim/skimage/_shared/_dependency_checks.py
cucim/skimage/_shared/_gradient.py
cucim/skimage/_shared/filters.py
cucim/skimage/_shared/fft.py
cucim/skimage/_shared/utils.py
cucim/skimage/_shared/testing.py
cucim/skimage/_shared/coord.py
cucim/skimage/_shared/version_requirements.py
cucim/skimage/_shared/_warnings.py
cucim/skimage/_shared/__init__.py
cucim/skimage/_shared/tests/test_utils.py
cucim/skimage/_shared/tests/test_warnings.py
cucim/skimage/transform/integral.py
cucim/skimage/transform/_geometric.py
cucim/skimage/transform/cufile.log
cucim/skimage/transform/pyramids.py
cucim/skimage/transform/_warps_temp_downscale.py
cucim/skimage/transform/_warps.py
cucim/skimage/transform/__init__.py
