Metadata-Version: 2.1
Name: cucim
Version: 23.10.0
Summary: cuCIM - an extensible toolkit designed to provide GPU accelerated I/O, computer vision & image processing primitives for N-Dimensional images with a focus on biomedical imaging.
Home-page: https://developer.nvidia.com/multidimensional-image-processing
Author: NVIDIA Corporation
License: Apache-2.0
Project-URL: Source, https://github.com/rapidsai/cucim
Project-URL: Documentation, https://docs.rapids.ai/api/cucim/stable/
Project-URL: Changelog, https://github.com/rapidsai/cucim/blob/main/CHANGELOG.md
Project-URL: Issue Tracker, https://github.com/rapidsai/cucim/issues
Platform: manylinux2014_x86_64
Classifier: Development Status :: 4 - Beta
Classifier: Intended Audience :: Developers
Classifier: Intended Audience :: Education
Classifier: Intended Audience :: Science/Research
Classifier: Intended Audience :: Healthcare Industry
Classifier: Operating System :: POSIX :: Linux
Classifier: Environment :: Console
Classifier: Environment :: GPU :: NVIDIA CUDA :: 11.0
Classifier: License :: OSI Approved :: Apache Software License
Classifier: Programming Language :: C++
Classifier: Programming Language :: Python
Classifier: Programming Language :: Python :: 3
Classifier: Programming Language :: Python :: 3.8
Classifier: Programming Language :: Python :: 3.9
Classifier: Programming Language :: Python :: 3.10
Classifier: Programming Language :: Python :: 3.11
Classifier: Topic :: Scientific/Engineering :: Image Processing
Requires-Python: >= 3.6
License-File: AUTHORS.md
Requires-Dist: click
Requires-Dist: numpy
Requires-Dist: lazy-loader (>=0.1)
